README.md
setup.py
irl2019/__init__.py
irl2019/binder.py
irl2019/gcs.py
irl2019/useful_snippets.py
irl2019.egg-info/PKG-INFO
irl2019.egg-info/SOURCES.txt
irl2019.egg-info/dependency_links.txt
irl2019.egg-info/not-zip-safe
irl2019.egg-info/requires.txt
irl2019.egg-info/top_level.txt