Metadata-Version: 1.0
Name: irl2019
Version: 0.9
Summary: Temporary package to support an event.
Home-page: UNKNOWN
Author: Matthew Honnibal
Author-email: matt@explosion.ai
License: MIT
Platform: UNKNOWN
